PythonProjectBootstrapperTest5/EntryPoint.py
PythonProjectBootstrapperTest5/Math.py
PythonProjectBootstrapperTest5/__init__.py
PythonProjectBootstrapperTest5-0.1.3.dist-info/LICENSE.txt
PythonProjectBootstrapperTest5-0.1.3.dist-info/METADATA
PythonProjectBootstrapperTest5-0.1.3.dist-info/WHEEL
PythonProjectBootstrapperTest5-0.1.3.dist-info/entry_points.txt
PythonProjectBootstrapperTest5-0.1.3.dist-info/top_level.txt
PythonProjectBootstrapperTest5-0.1.3.dist-info/RECORD
